{"dates": "Wed May 19 13:16:52 +0000 2021", "user_name": "Arie Achmad", "text": "@cateringasma @thejanur2 \n@elwis_renggiansyaah \n@iamranigalerimanten \n#weddingvendor \n#weddingportrait\u2026 https://t.co/qdCuvwxUHQ", "latitude": -3.2917, "longitude": 102.8702, "place": {"id": "9688346ffd007367", "url": "https://api.twitter.com/1.1/geo/id/9688346ffd007367.json", "place_type": "city", "name": "Lubuk Linggau Barat", "full_name": "Lubuk Linggau Barat, Indonesia", "country_code": "ID", "country": "Indonesia", "bounding_box": {"type": "Polygon", "coordinates": [[[102.773888, -3.341087], [102.773888, -3.21243], [102.897949, -3.21243], [102.897949, -3.341087]]]}, "attributes": {}}, "id_place": "9688346ffd007367"}