{"dates": "Tue May 18 20:49:10 +0000 2021", "user_name": "Aditya Shinde", "text": "Tung Fort Trek \n\n#throwback #trek #instagram #forts @ Tung Fort https://t.co/RUt1s9x5MN", "latitude": 18.6603, "longitude": 73.4631, "place": {"id": "21cec9a8b900c81c", "url": "https://api.twitter.com/1.1/geo/id/21cec9a8b900c81c.json", "place_type": "city", "name": "Lonavala", "full_name": "Lonavala, India", "country_code": "IN", "country": "India", "bounding_box": {"type": "Polygon", "coordinates": [[[73.3317, 18.591501], [73.3317, 18.981856], [73.774005, 18.981856], [73.774005, 18.591501]]]}, "attributes": {}}, "id_place": "21cec9a8b900c81c"}